india_housing_datasets/__init__.py
india_housing_datasets/ahmedabad.py
india_housing_datasets/gurugram.py
india_housing_datasets/mumbai.py
india_housing_datasets/data/ahmedabad_housing.csv
india_housing_datasets/data/gurugram_housing.csv
india_housing_datasets/data/mumbai_housing.csv
india_housing_datasets-0.1.0.dist-info/licenses/LICENSE
india_housing_datasets-0.1.0.dist-info/METADATA
india_housing_datasets-0.1.0.dist-info/WHEEL
india_housing_datasets-0.1.0.dist-info/top_level.txt
india_housing_datasets-0.1.0.dist-info/RECORD
