Metadata-Version: 2.4
Name: india_housing_datasets
Version: 0.1.0
Summary: A collection of clean Indian city housing datasets (Ahmedabad, Gurugram, Mumbai).
Home-page: https://github.com/Rvbaghel/india_housing_datasets
Author: Vishal Baghel
Author-email: baghelvishal264@gmail.com
License: MIT
Classifier: Programming Language :: Python :: 3
Classifier: License :: OSI Approved :: MIT License
Classifier: Operating System :: OS Independent
Requires-Python: >=3.7
License-File: LICENSE
Requires-Dist: pandas>=1.3.0
Dynamic: author
Dynamic: author-email
Dynamic: classifier
Dynamic: description
Dynamic: description-content-type
Dynamic: home-page
Dynamic: license
Dynamic: license-file
Dynamic: requires-dist
Dynamic: requires-python
Dynamic: summary
